Workbook
Name Slicer_Designation: #N/A
Name Slicer_SER_TYPE: #N/A
Name Slicer_SH_DOMAIN: #N/A

Sheet Status
A1: SH_ID | B1: Current_Status | C1: Sent_date | D1: Delivery_date
A2: 690 | B2: DELIVERED | C2: 41757 | D2: 41991
A3: 933 | B3: DELIVERED | C3: 35595 | D3: 35621
A4: 261 | B4: NOT DELIVERED | C4: 34195
A5: 445 | B5: NOT DELIVERED | C5: 43812
A6: 722 | B6: NOT DELIVERED | C6: 35329
A7: 129 | B7: DELIVERED | C7: 26046 | D7: 26238
A8: 489 | B8: NOT DELIVERED | C8: 38707
A9: 165 | B9: NOT DELIVERED | C9: 29039
A10: 164 | B10: NOT DELIVERED | C10: 27879
A11: 364 | B11: NOT DELIVERED | C11: 40971
A12: 469 | B12: DELIVERED | C12: 33287 | D12: 33373
A13: 158 | B13: DELIVERED | C13: 27850 | D13: 27941
A14: 337 | B14: NOT DELIVERED | C14: 27891
A15: 634 | B15: NOT DELIVERED | C15: 29501
A16: 577 | B16: DELIVERED | C16: 31855 | D16: 31998
A17: 907 | B17: NOT DELIVERED | C17: 41478
A18: 870 | B18: NOT DELIVERED | C18: 40239
A19: 982 | B19: NOT DELIVERED | C19: 43025
A20: 351 | B20: DELIVERED | C20: 28128 | D20: 28312
A21: 328 | B21: DELIVERED | C21: 35450 | D21: 35681
A22: 242 | B22: NOT DELIVERED | C22: 35408
A23: 421 | B23: DELIVERED | C23: 36198 | D23: 36224
A24: 6 | B24: DELIVERED | C24: 28192 | D24: 28437
A25: 384 | B25: NOT DELIVERED | C25: 26350
A26: 286 | B26: DELIVERED | C26: 38509 | D26: 38610
A27: 892 | B27: DELIVERED | C27: 43786 | D27: 43811
A28: 558 | B28: DELIVERED | C28: 41574 | D28: 41593
A29: 481 | B29: NOT DELIVERED | C29: 38909
A30: 155 | B30: NOT DELIVERED | C30: 37887
A31: 771 | B31: DELIVERED | C31: 41397 | D31: 41593
A32: 945 | B32: DELIVERED | C32: 37010 | D32: 37113
A33: 719 | B33: DELIVERED | C33: 38739 | D33: 38915
A34: 493 | B34: NOT DELIVERED | C34: 34931
A35: 998 | B35: DELIVERED | C35: 41599 | D35: 41593
A36: 968 | B36: DELIVERED | C36: 33973 | D36: 34183
A37: 738 | B37: NOT DELIVERED | C37: 28387
A38: 912 | B38: NOT DELIVERED | C38: 43829
A39: 782 | B39: DELIVERED | C39: 37499 | D39: 37549
A40: 140 | B40: DELIVERED | C40: 38878 | D40: 38915
A41: 702 | B41: DELIVERED | C41: 38175 | D41: 38311
A42: 284 | B42: DELIVERED | C42: 29988 | D42: 30018
A43: 199 | B43: NOT DELIVERED | C43: 39290
A44: 228 | B44: DELIVERED | C44: 34423 | D44: 34433
A45: 908 | B45: NOT DELIVERED | C45: 36188
A46: 594 | B46: NOT DELIVERED | C46: 38066
A47: 542 | B47: NOT DELIVERED | C47: 31551
A48: 586 | B48: NOT DELIVERED | C48: 28192
A49: 636 | B49: DELIVERED | C49: 39502 | D49: 39669
A50: 581 | B50: NOT DELIVERED | C50: 43063
A51: 336 | B51: NOT DELIVERED | C51: 26581
A52: 504 | B52: DELIVERED | C52: 30143 | D52: 30239
A53: 346 | B53: DELIVERED | C53: 39238 | D53: 39275
A54: 135 | B54: NOT DELIVERED | C54: 38240
A55: 822 | B55: DELIVERED | C55: 33419 | D55: 33434
A56: 95 | B56: NOT DELIVERED | C56: 41375
A57: 597 | B57: NOT DELIVERED | C57: 40385
A58: 340 | B58: NOT DELIVERED | C58: 29893
A59: 905 | B59: DELIVERED | C59: 30417 | D59: 30589
A60: 250 | B60: DELIVERED | C60: 38978 | D60: 39012
A61: 400 | B61: NOT DELIVERED | C61: 37628
A62: 877 | B62: DELIVERED | C62: 36550 | D62: 36607
A63: 97 | B63: NOT DELIVERED | C63: 40688
A64: 12 | B64: NOT DELIVERED | C64: 36695
A65: 353 | B65: DELIVERED | C65: 41123 | D65: 41186
A66: 856 | B66: DELIVERED | C66: 28302 | D66: 28437
A67: 1 | B67: DELIVERED | C67: 40222 | D67: 40512
A68: 390 | B68: DELIVERED | C68: 39896 | D68: 39881
A69: 446 | B69: NOT DELIVERED | C69: 34084
A70: 32 | B70: NOT DELIVERED | C70: 38229
A71: 420 | B71: NOT DELIVERED | C71: 32510
A72: 708 | B72: DELIVERED | C72: 43515 | D72: 43677
A73: 227 | B73: DELIVERED | C73: 37281 | D73: 37261
A74: 595 | B74: NOT DELIVERED | C74: 37751
A75: 211 | B75: DELIVERED | C75: 38793 | D75: 39074
A76: 650 | B76: NOT DELIVERED | C76: 39251
A77: 45 | B77: DELIVERED | C77: 35127 | D77: 35186
A78: 201 | B78: NOT DELIVERED | C78: 30287
A79: 564 | B79: DELIVERED | C79: 38109 | D79: 38255
A80: 138 | B80: NOT DELIVERED | C80: 39500
A81: 57 | B81: DELIVERED | C81: 38064 | D81: 38048
A82: 128 | B82: NOT DELIVERED | C82: 33685
A83: 33 | B83: NOT DELIVERED | C83: 32238
A84: 936 | B84: NOT DELIVERED | C84: 41314
A85: 762 | B85: NOT DELIVERED | C85: 28570
A86: 838 | B86: DELIVERED | C86: 34704 | D86: 34934
A87: 215 | B87: DELIVERED | C87: 31057 | D87: 31078
A88: 818 | B88: DELIVERED | C88: 38957 | D88: 39010
A89: 780 | B89: DELIVERED | C89: 32793 | D89: 32798
A90: 40 | B90: NOT DELIVERED | C90: 29344
A91: 366 | B91: DELIVERED | C91: 29281 | D91: 29296
A92: 678 | B92: NOT DELIVERED | C92: 34349
A93: 703 | B93: NOT DELIVERED | C93: 42760
A94: 180 | B94: NOT DELIVERED | C94: 27485
A95: 214 | B95: DELIVERED | C95: 31842 | D95: 31998
A96: 408 | B96: DELIVERED | C96: 32925 | D96: 33127
A97: 902 | B97: DELIVERED | C97: 32514 | D97: 32768
A98: 763 | B98: DELIVERED | C98: 41819 | D98: 41891
A99: 168 | B99: DELIVERED | C99: 35435 | D99: 35593
A100: 723 | B100: NOT DELIVERED | C100: 29790
...

Sheet Pivot_Avg_Weight
A3: Row Labels | B3: Average of SH_WEIGHT
A4: Express | B4: 569.45098
A5: Regular | B5: 472.64286
A6: Grand Total | B6: 522.015

Sheet Shipment_Domain_Comparison
A3: Row Labels | B3: Count of SH_DOMAIN
A4: Domestic | B4: 109
A5: International | B5: 91
A6: Grand Total | B6: 200

Sheet Avg_delivery_time
A3: Row Labels | B3: Average of Delivery_Time
A4: Domestic | B4: 117.98
A5: International | B5: 96.26
A6: Grand Total | B6: 107.12

Sheet Shipment_efficiency_analysis
A3: Row Labels | B3: Average of Efficiency
A4: Domestic | B4: 0.53887399
A5: Express | B5: 0.53887399
A6: Grand Total | B6: 0.53887399

Sheet Shipment_Details
A1: SH_ID | B1: C_ID | C1: SH_CONTENT | D1: SH_DOMAIN | E1: SER_TYPE | F1: SH_WEIGHT | G1: SH_CHARGES | H1: SR_ADDR | I1: DS_ADDR | J1: Current_Status | K1: Sent_Date | L1: Delivery_Date | M1: Weight_Category | N1: Delivery_Time | O1: Efficiency
A2: 690 | B2: 230 | C2: Healthcare | D2: Domestic | E2: Regular | F2: 553 | G2: 1210 | H2: 1800 Block of 26TH ST | I2: 1200 Block of JACKSON ST | J2: =_xlfn.XLOOKUP(A2,Status!A:A,Status!B:B) -> DELIVERED | K2: =_xlfn.XLOOKUP(A2,Status!A:A,Status!C:C) -> 41757 | L2: =_xlfn.XLOOKUP(A2,Status!A:A,Status!D:D) -> 41991 | M2: =IF(F2>500,"Heavy","Light") -> Heavy | N2: =IF(OR(L2=0,K2=0),"",ABS(L2-K2)) -> 234 | O2: =F2/G2 -> 0.45702479
A3: 933 | B3: 3189 | C3: Healthcare | D3: International | E3: Express | F3: 810 | G3: 1114 | H3: 2600 Block of ALEMANY BL | I3: 700 Block of HAMPSHIRE ST | J3: =_xlfn.XLOOKUP(A3,Status!A:A,Status!B:B) -> DELIVERED | K3: =_xlfn.XLOOKUP(A3,Status!A:A,Status!C:C) -> 35595 | L3: =_xlfn.XLOOKUP(A3,Status!A:A,Status!D:D) -> 35621 | M3: =IF(F3>500,"Heavy","Light") -> Heavy | N3: =IF(OR(L3=0,K3=0),"",ABS(L3-K3)) -> 26 | O3: =F3/G3 -> 0.72710952
A4: 261 | B4: 2216 | C4: Luggage | D4: Domestic | E4: Express | F4: 994 | G4: 1020 | H4: BARTLETT ST / 23RD ST | I4: 500 Block of HAIGHT ST | J4: =_xlfn.XLOOKUP(A4,Status!A:A,Status!B:B) -> NOT DELIVERED | K4: =_xlfn.XLOOKUP(A4,Status!A:A,Status!C:C) -> 34195 | L4: =_xlfn.XLOOKUP(A4,Status!A:A,Status!D:D) -> 0 | M4: =IF(F4>500,"Heavy","Light") -> Heavy | N4: =IF(OR(L4=0,K4=0),"",ABS(L4-K4)) | O4: =F4/G4 -> 0.9745098
A5: 445 | B5: 1904 | C5: Home Furnishing | D5: Domestic | E5: Express | F5: 598 | G5: 1351 | H5: 1300 Block of 7TH AV | I5: 300 Block of 9TH ST | J5: =_xlfn.XLOOKUP(A5,Status!A:A,Status!B:B) -> NOT DELIVERED | K5: =_xlfn.XLOOKUP(A5,Status!A:A,Status!C:C) -> 43812 | L5: =_xlfn.XLOOKUP(A5,Status!A:A,Status!D:D) -> 0 | M5: =IF(F5>500,"Heavy","Light") -> Heavy | N5: =IF(OR(L5=0,K5=0),"",ABS(L5-K5)) | O5: =F5/G5 -> 0.44263509
A6: 722 | B6: 7342 | C6: Electronics | D6: International | E6: Express | F6: 412 | G6: 566 | H6: 0 Block of EUREKA ST | I6: 1800 Block of VANNESS AV | J6: =_xlfn.XLOOKUP(A6,Status!A:A,Status!B:B) -> NOT DELIVERED | K6: =_xlfn.XLOOKUP(A6,Status!A:A,Status!C:C) -> 35329 | L6: =_xlfn.XLOOKUP(A6,Status!A:A,Status!D:D) -> 0 | M6: =IF(F6>500,"Heavy","Light") -> Light | N6: =IF(OR(L6=0,K6=0),"",ABS(L6-K6)) | O6: =F6/G6 -> 0.72791519
A7: 129 | B7: 7633 | C7: Food and Beverages | D7: Domestic | E7: Regular | F7: 379 | G7: 590 | H7: 700 Block of VANNESS AV | I7: 500 Block of LEAVENWORTH ST | J7: =_xlfn.XLOOKUP(A7,Status!A:A,Status!B:B) -> DELIVERED | K7: =_xlfn.XLOOKUP(A7,Status!A:A,Status!C:C) -> 26046 | L7: =_xlfn.XLOOKUP(A7,Status!A:A,Status!D:D) -> 26238 | M7: =IF(F7>500,"Heavy","Light") -> Light | N7: =IF(OR(L7=0,K7=0),"",ABS(L7-K7)) -> 192 | O7: =F7/G7 -> 0.64237288
A8: 489 | B8: 2154 | C8: Fashion | D8: Domestic | E8: Regular | F8: 892 | G8: 1407 | H8: 200 Block of BERRY ST | I8: CARROLL AV / JENNINGS ST | J8: =_xlfn.XLOOKUP(A8,Status!A:A,Status!B:B) -> NOT DELIVERED | K8: =_xlfn.XLOOKUP(A8,Status!A:A,Status!C:C) -> 38707 | L8: =_xlfn.XLOOKUP(A8,Status!A:A,Status!D:D) -> 0 | M8: =IF(F8>500,"Heavy","Light") -> Heavy | N8: =IF(OR(L8=0,K8=0),"",ABS(L8-K8)) | O8: =F8/G8 -> 0.63397299
A9: 165 | B9: 5543 | C9: Industrial Equipments | D9: Domestic | E9: Regular | F9: 347 | G9: 786 | H9: 1100 Block of FRANCISCO ST | I9: 1000 Block of MARKET ST | J9: =_xlfn.XLOOKUP(A9,Status!A:A,Status!B:B) -> NOT DELIVERED | K9: =_xlfn.XLOOKUP(A9,Status!A:A,Status!C:C) -> 29039 | L9: =_xlfn.XLOOKUP(A9,Status!A:A,Status!D:D) -> 0 | M9: =IF(F9>500,"Heavy","Light") -> Light | N9: =IF(OR(L9=0,K9=0),"",ABS(L9-K9)) | O9: =F9/G9 -> 0.44147583
A10: 164 | B10: 2332 | C10: Hazardous Goods | D10: International | E10: Express | F10: 457 | G10: 855 | H10: 100 Block of NEWMONTGOMERY ST | I10: 600 Block of SOUTH VAN NESS AV | J10: =_xlfn.XLOOKUP(A10,Status!A:A,Status!B:B) -> NOT DELIVERED | K10: =_xlfn.XLOOKUP(A10,Status!A:A,Status!C:C) -> 27879 | L10: =_xlfn.XLOOKUP(A10,Status!A:A,Status!D:D) -> 0 | M10: =IF(F10>500,"Heavy","Light") -> Light | N10: =IF(OR(L10=0,K10=0),"",ABS(L10-K10)) | O10: =F10/G10 -> 0.53450292
A11: 364 | B11: 4094 | C11: Automotive | D11: International | E11: Express | F11: 957 | G11: 1182 | H11: 200 Block of SCOTT ST | I11: 2600 Block of MISSION ST | J11: =_xlfn.XLOOKUP(A11,Status!A:A,Status!B:B) -> NOT DELIVERED | K11: =_xlfn.XLOOKUP(A11,Status!A:A,Status!C:C) -> 40971 | L11: =_xlfn.XLOOKUP(A11,Status!A:A,Status!D:D) -> 0 | M11: =IF(F11>500,"Heavy","Light") -> Heavy | N11: =IF(OR(L11=0,K11=0),"",ABS(L11-K11)) | O11: =F11/G11 -> 0.80964467
A12: 469 | B12: 3042 | C12: Electronics | D12: International | E12: Regular | F12: 23 | G12: 25 | H12: BELVEDERE ST / WALLER ST | I12: 0 Block of CEDAR ST | J12: =_xlfn.XLOOKUP(A12,Status!A:A,Status!B:B) -> DELIVERED | K12: =_xlfn.XLOOKUP(A12,Status!A:A,Status!C:C) -> 33287 | L12: =_xlfn.XLOOKUP(A12,Status!A:A,Status!D:D) -> 33373 | M12: =IF(F12>500,"Heavy","Light") -> Light | N12: =IF(OR(L12=0,K12=0),"",ABS(L12-K12)) -> 86 | O12: =F12/G12 -> 0.92
A13: 158 | B13: 2220 | C13: Healthcare | D13: Domestic | E13: Express | F13: 479 | G13: 861 | H13: 800 Block of BRYANT ST | I13: 500 Block of FREDERICK ST | J13: =_xlfn.XLOOKUP(A13,Status!A:A,Status!B:B) -> DELIVERED | K13: =_xlfn.XLOOKUP(A13,Status!A:A,Status!C:C) -> 27850 | L13: =_xlfn.XLOOKUP(A13,Status!A:A,Status!D:D) -> 27941 | M13: =IF(F13>500,"Heavy","Light") -> Light | N13: =IF(OR(L13=0,K13=0),"",ABS(L13-K13)) -> 91 | O13: =F13/G13 -> 0.55632985
... A201: 579 | B201: 4892 | C201: Home Furnishing | D201: Domestic | E201: Express | F201: 913 | G201: 1385 | H201: SUTTER ST / LAGUNA ST | I201: SOUTH VAN NESS AV / 22ND ST | J201: =_xlfn.XLOOKUP(A201,Status!A:A,Status!B:B) -> NOT DELIVERED | K201: =_xlfn.XLOOKUP(A201,Status!A:A,Status!C:C) -> 42725 | L201: =_xlfn.XLOOKUP(A201,Status!A:A,Status!D:D) -> 0 | M201: =IF(F201>500,"Heavy","Light") -> Heavy | N201: =IF(OR(L201=0,K201=0),"",ABS(L201-K201)) | O201: =F201/G201 -> 0.65920578

Sheet Top_5_Customer
A3: Row Labels | B3: Sum of AMOUNT
A4: 1334 | B4: 99604
A5: 175 | B5: 99492
A6: 207 | B6: 99367
A7: 2154 | B7: 99239
A8: 3 | B8: 98982
A9: Grand Total | B9: 496684

Sheet Payment_Summary_PT
A3: Average of AMOUNT | B3: Column Labels
A4: Row Labels | B4: NOT PAID | C4: PAID | D4: Grand Total
A5: CARD PAYMENT | B5: 44552.714 | C5: 45570.378 | D5: 45039.894
A6: COD | B6: 48273.686 | C6: 50789.109 | D6: 49578.858
A7: Grand Total | B7: 46450.41 | C7: 48440.68 | D7: 47445.545

Sheet Dynamic_payment_analysis
A3: Row Labels | B3: Average of AMOUNT
A4: CARD PAYMENT | B4: 45039.894
A5: COD | B5: 49578.858
A6: Grand Total | B6: 47445.545

Sheet Payment_Details
A1: Payment_ID | B1: C_ID | C1: SH_ID | D1: AMOUNT | E1: Payment_Status | F1: Payment_Mode | G1: Payment_Date | H1: Payment_Category | I1: Total_Customer_Payment
A2: 313cd69e-66f3-11ea-9879-7077813058ce | B2: 230 | C2: 690 | D2: 49302 | E2: PAID | F2: CARD PAYMENT | G2: 41991 | H2: =IF(D2>7000,"High",IF(D2>3000,"Medium","Low")) -> High | I2: =SUMIF(B:B,B2,D:D) -> 49302
A3: 313dc140-66f3-11ea-a952-7077813058ce | B3: 3189 | C3: 933 | D3: 78698 | E3: PAID | F3: CARD PAYMENT | G3: 35621 | H3: =IF(D3>7000,"High",IF(D3>3000,"Medium","Low")) -> High | I3: =SUMIF(B:B,B3,D:D) -> 78698
A4: 313eab1e-66f3-11ea-81af-7077813058ce | B4: 2216 | C4: 261 | D4: 69417 | E4: NOT PAID | F4: CARD PAYMENT | H4: =IF(D4>7000,"High",IF(D4>3000,"Medium","Low")) -> High | I4: =SUMIF(B:B,B4,D:D) -> 69417
A5: 313f474a-66f3-11ea-a78b-7077813058ce | B5: 1904 | C5: 445 | D5: 39655 | E5: NOT PAID | F5: COD | H5: =IF(D5>7000,"High",IF(D5>3000,"Medium","Low")) -> High | I5: =SUMIF(B:B,B5,D:D) -> 39655
A6: 3140589a-66f3-11ea-a057-7077813058ce | B6: 7342 | C6: 722 | D6: 87400 | E6: NOT PAID | F6: COD | H6: =IF(D6>7000,"High",IF(D6>3000,"Medium","Low")) -> High | I6: =SUMIF(B:B,B6,D:D) -> 87400
A7: 31411bc8-66f3-11ea-a4b7-7077813058ce | B7: 7633 | C7: 129 | D7: 56881 | E7: PAID | F7: CARD PAYMENT | G7: 26238 | H7: =IF(D7>7000,"High",IF(D7>3000,"Medium","Low")) -> High | I7: =SUMIF(B:B,B7,D:D) -> 56881
A8: 3141defa-66f3-11ea-b10e-7077813058ce | B8: 2154 | C8: 489 | D8: 99239 | E8: NOT PAID | F8: COD | H8: =IF(D8>7000,"High",IF(D8>3000,"Medium","Low")) -> High | I8: =SUMIF(B:B,B8,D:D) -> 99239
A9: 3142c940-66f3-11ea-9f69-7077813058ce | B9: 5543 | C9: 165 | D9: 23921 | E9: NOT PAID | F9: COD | H9: =IF(D9>7000,"High",IF(D9>3000,"Medium","Low")) -> High | I9: =SUMIF(B:B,B9,D:D) -> 23921
A10: 31444fa8-66f3-11ea-912a-7077813058ce | B10: 2332 | C10: 164 | D10: 67599 | E10: NOT PAID | F10: CARD PAYMENT | H10: =IF(D10>7000,"High",IF(D10>3000,"Medium","Low")) -> High | I10: =SUMIF(B:B,B10,D:D) -> 67599
A11: 314539e6-66f3-11ea-bfa4-7077813058ce | B11: 4094 | C11: 364 | D11: 3725 | E11: NOT PAID | F11: COD | H11: =IF(D11>7000,"High",IF(D11>3000,"Medium","Low")) -> Medium | I11: =SUMIF(B:B,B11,D:D) -> 3725
A12: 3145fd0a-66f3-11ea-958b-7077813058ce | B12: 3042 | C12: 469 | D12: 95516 | E12: PAID | F12: COD | G12: 33373 | H12: =IF(D12>7000,"High",IF(D12>3000,"Medium","Low")) -> High | I12: =SUMIF(B:B,B12,D:D) -> 95516
A13: 31469934-66f3-11ea-8572-7077813058ce | B13: 2220 | C13: 158 | D13: 62528 | E13: PAID | F13: COD | G13: 27941 | H13: =IF(D13>7000,"High",IF(D13>3000,"Medium","Low")) -> High | I13: =SUMIF(B:B,B13,D:D) -> 62528
A14: 3147355e-66f3-11ea-aae4-7077813058ce | B14: 4988 | C14: 337 | D14: 21021 | E14: NOT PAID | F14: CARD PAYMENT | H14: =IF(D14>7000,"High",IF(D14>3000,"Medium","Low")) -> High | I14: =SUMIF(B:B,B14,D:D) -> 21021
A15: 3147f89c-66f3-11ea-8dfd-7077813058ce | B15: 175 | C15: 634 | D15: 99492 | E15: NOT PAID | F15: CARD PAYMENT | H15: =IF(D15>7000,"High",IF(D15>3000,"Medium","Low")) -> High | I15: =SUMIF(B:B,B15,D:D) -> 99492
A16: 3148bbc8-66f3-11ea-8acf-7077813058ce | B16: 4233 | C16: 577 | D16: 60282 | E16: PAID | F16: CARD PAYMENT | G16: 31998 | H16: =IF(D16>7000,"High",IF(D16>3000,"Medium","Low")) -> High | I16: =SUMIF(B:B,B16,D:D) -> 60282
A17: 31497efa-66f3-11ea-9497-7077813058ce | B17: 4351 | C17: 907 | D17: 20357 | E17: NOT PAID | F17: CARD PAYMENT | H17: =IF(D17>7000,"High",IF(D17>3000,"Medium","Low")) -> High | I17: =SUMIF(B:B,B17,D:D) -> 20357
A18: 314a1b22-66f3-11ea-9e82-7077813058ce | B18: 5578 | C18: 870 | D18: 24053 | E18: NOT PAID | F18: CARD PAYMENT | H18: =IF(D18>7000,"High",IF(D18>3000,"Medium","Low")) -> High | I18: =SUMIF(B:B,B18,D:D) -> 24053
A19: 314ade58-66f3-11ea-8979-7077813058ce | B19: 4523 | C19: 982 | D19: 50958 | E19: NOT PAID | F19: CARD PAYMENT | H19: =IF(D19>7000,"High",IF(D19>3000,"Medium","Low")) -> High | I19: =SUMIF(B:B,B19,D:D) -> 50958
A20: 314b7a8a-66f3-11ea-97d4-7077813058ce | B20: 2972 | C20: 351 | D20: 68227 | E20: PAID | F20: CARD PAYMENT | G20: 28312 | H20: =IF(D20>7000,"High",IF(D20>3000,"Medium","Low")) -> High | I20: =SUMIF(B:B,B20,D:D) -> 68227
A21: 314c8bcc-66f3-11ea-b526-7077813058ce | B21: 6153 | C21: 328 | D21: 77861 | E21: PAID | F21: CARD PAYMENT | G21: 35681 | H21: =IF(D21>7000,"High",IF(D21>3000,"Medium","Low")) -> High | I21: =SUMIF(B:B,B21,D:D) -> 77861
A22: 314d761e-66f3-11ea-b155-7077813058ce | B22: 4852 | C22: 242 | D22: 48315 | E22: NOT PAID | F22: CARD PAYMENT | H22: =IF(D22>7000,"High",IF(D22>3000,"Medium","Low")) -> High | I22: =SUMIF(B:B,B22,D:D) -> 48315
A23: 314eae64-66f3-11ea-b08f-7077813058ce | B23: 8106 | C23: 421 | D23: 83002 | E23: PAID | F23: CARD PAYMENT | G23: 36224 | H23: =IF(D23>7000,"High",IF(D23>3000,"Medium","Low")) -> High | I23: =SUMIF(B:B,B23,D:D) -> 83002
A24: 314f4a7a-66f3-11ea-8b83-7077813058ce | B24: 3917 | C24: 6 | D24: 47650 | E24: PAID | F24: COD | G24: 28437 | H24: =IF(D24>7000,"High",IF(D24>3000,"Medium","Low")) -> High | I24: =SUMIF(B:B,B24,D:D) -> 47650
A25: 315034c6-66f3-11ea-a2bf-7077813058ce | B25: 9377 | C25: 384 | D25: 19386 | E25: NOT PAID | F25: COD | H25: =IF(D25>7000,"High",IF(D25>3000,"Medium","Low")) -> High | I25: =SUMIF(B:B,B25,D:D) -> 19386
A26: 31511efa-66f3-11ea-bc4c-7077813058ce | B26: 5387 | C26: 286 | D26: 39432 | E26: PAID | F26: COD | G26: 38610 | H26: =IF(D26>7000,"High",IF(D26>3000,"Medium","Low")) -> High | I26: =SUMIF(B:B,B26,D:D) -> 39432
A27: 3151e23a-66f3-11ea-9b38-7077813058ce | B27: 6513 | C27: 892 | D27: 1421 | E27: PAID | F27: COD | G27: 43811 | H27: =IF(D27>7000,"High",IF(D27>3000,"Medium","Low")) -> Low | I27: =SUMIF(B:B,B27,D:D) -> 1421
A28: 3152a56c-66f3-11ea-9340-7077813058ce | B28: 3965 | C28: 558 | D28: 16113 | E28: PAID | F28: COD | G28: 41593 | H28: =IF(D28>7000,"High",IF(D28>3000,"Medium","Low")) -> High | I28: =SUMIF(B:B,B28,D:D) -> 16113
A29: 31534188-66f3-11ea-8acd-7077813058ce | B29: 8893 | C29: 481 | D29: 52318 | E29: NOT PAID | F29: CARD PAYMENT | H29: =IF(D29>7000,"High",IF(D29>3000,"Medium","Low")) -> High | I29: =SUMIF(B:B,B29,D:D) -> 52318
A30: 3153ddb4-66f3-11ea-a4d6-7077813058ce | B30: 1897 | C30: 155 | D30: 7389 | E30: NOT PAID | F30: CARD PAYMENT | H30: =IF(D30>7000,"High",IF(D30>3000,"Medium","Low")) -> High | I30: =SUMIF(B:B,B30,D:D) -> 7389
A31: 3154c800-66f3-11ea-8721-7077813058ce | B31: 390 | C31: 771 | D31: 86040 | E31: PAID | F31: COD | G31: 41593 | H31: =IF(D31>7000,"High",IF(D31>3000,"Medium","Low")) -> High | I31: =SUMIF(B:B,B31,D:D) -> 86040
A32: 3155d94c-66f3-11ea-b116-7077813058ce | B32: 3633 | C32: 945 | D32: 56148 | E32: PAID | F32: COD | G32: 37113 | H32: =IF(D32>7000,"High",IF(D32>3000,"Medium","Low")) -> High | I32: =SUMIF(B:B,B32,D:D) -> 56148
A33: 31575fac-66f3-11ea-8d99-7077813058ce | B33: 7828 | C33: 719 | D33: 894 | E33: PAID | F33: CARD PAYMENT | G33: 38915 | H33: =IF(D33>7000,"High",IF(D33>3000,"Medium","Low")) -> Low | I33: =SUMIF(B:B,B33,D:D) -> 894
A34: 315897f8-66f3-11ea-ad46-7077813058ce | B34: 2241 | C34: 493 | D34: 35634 | E34: NOT PAID | F34: COD | H34: =IF(D34>7000,"High",IF(D34>3000,"Medium","Low")) -> High | I34: =SUMIF(B:B,B34,D:D) -> 35634
A35: 3159d04c-66f3-11ea-95df-7077813058ce | B35: 896 | C35: 998 | D35: 28701 | E35: PAID | F35: CARD PAYMENT | G35: 41593 | H35: =IF(D35>7000,"High",IF(D35>3000,"Medium","Low")) -> High | I35: =SUMIF(B:B,B35,D:D) -> 28701
A36: 315aba8a-66f3-11ea-9db6-7077813058ce | B36: 6361 | C36: 968 | D36: 90380 | E36: PAID | F36: CARD PAYMENT | G36: 34183 | H36: =IF(D36>7000,"High",IF(D36>3000,"Medium","Low")) -> High | I36: =SUMIF(B:B,B36,D:D) -> 90380
A37: 315b7db4-66f3-11ea-ae41-7077813058ce | B37: 6713 | C37: 738 | D37: 21813 | E37: NOT PAID | F37: COD | H37: =IF(D37>7000,"High",IF(D37>3000,"Medium","Low")) -> High | I37: =SUMIF(B:B,B37,D:D) -> 21813
A38: 315c67f4-66f3-11ea-bcd7-7077813058ce | B38: 4283 | C38: 912 | D38: 36312 | E38: NOT PAID | F38: CARD PAYMENT | H38: =IF(D38>7000,"High",IF(D38>3000,"Medium","Low")) -> High | I38: =SUMIF(B:B,B38,D:D) -> 36312
A39: 315d041c-66f3-11ea-8af9-7077813058ce | B39: 9486 | C39: 782 | D39: 24856 | E39: PAID | F39: CARD PAYMENT | G39: 37549 | H39: =IF(D39>7000,"High",IF(D39>3000,"Medium","Low")) -> High | I39: =SUMIF(B:B,B39,D:D) -> 24856
A40: 315da042-66f3-11ea-ac04-7077813058ce | B40: 308 | C40: 140 | D40: 39234 | E40: PAID | F40: CARD PAYMENT | G40: 38915 | H40: =IF(D40>7000,"High",IF(D40>3000,"Medium","Low")) -> High | I40: =SUMIF(B:B,B40,D:D) -> 39234
A41: 315e3c68-66f3-11ea-8d08-7077813058ce | B41: 8927 | C41: 702 | D41: 74222 | E41: PAID | F41: COD | G41: 38311 | H41: =IF(D41>7000,"High",IF(D41>3000,"Medium","Low")) -> High | I41: =SUMIF(B:B,B41,D:D) -> 74222
A42: 315f26ac-66f3-11ea-a883-7077813058ce | B42: 249 | C42: 284 | D42: 47260 | E42: PAID | F42: CARD PAYMENT | G42: 30018 | H42: =IF(D42>7000,"High",IF(D42>3000,"Medium","Low")) -> High | I42: =SUMIF(B:B,B42,D:D) -> 47260
A43: 315fe9e2-66f3-11ea-b80f-7077813058ce | B43: 2620 | C43: 199 | D43: 45432 | E43: NOT PAID | F43: COD | H43: =IF(D43>7000,"High",IF(D43>3000,"Medium","Low")) -> High | I43: =SUMIF(B:B,B43,D:D) -> 45432
A44: 3160ad0c-66f3-11ea-961a-7077813058ce | B44: 1164 | C44: 228 | D44: 30192 | E44: PAID | F44: COD | G44: 34433 | H44: =IF(D44>7000,"High",IF(D44>3000,"Medium","Low")) -> High | I44: =SUMIF(B:B,B44,D:D) -> 30192
A45: 31619754-66f3-11ea-911d-7077813058ce | B45: 4711 | C45: 908 | D45: 53868 | E45: NOT PAID | F45: CARD PAYMENT | H45: =IF(D45>7000,"High",IF(D45>3000,"Medium","Low")) -> High | I45: =SUMIF(B:B,B45,D:D) -> 53868
A46: 3162337a-66f3-11ea-bf3c-7077813058ce | B46: 4053 | C46: 594 | D46: 9691 | E46: NOT PAID | F46: CARD PAYMENT | H46: =IF(D46>7000,"High",IF(D46>3000,"Medium","Low")) -> High | I46: =SUMIF(B:B,B46,D:D) -> 9691
A47: 3162cf9c-66f3-11ea-917a-7077813058ce | B47: 4272 | C47: 542 | D47: 39001 | E47: NOT PAID | F47: COD | H47: =IF(D47>7000,"High",IF(D47>3000,"Medium","Low")) -> High | I47: =SUMIF(B:B,B47,D:D) -> 39001
A48: 31636bd2-66f3-11ea-aa21-7077813058ce | B48: 7005 | C48: 586 | D48: 70814 | E48: NOT PAID | F48: CARD PAYMENT | H48: =IF(D48>7000,"High",IF(D48>3000,"Medium","Low")) -> High | I48: =SUMIF(B:B,B48,D:D) -> 70814
A49: 31642f12-66f3-11ea-b553-7077813058ce | B49: 2308 | C49: 636 | D49: 13740 | E49: PAID | F49: COD | G49: 39669 | H49: =IF(D49>7000,"High",IF(D49>3000,"Medium","Low")) -> High | I49: =SUMIF(B:B,B49,D:D) -> 13740
A50: 3164f24c-66f3-11ea-bf87-7077813058ce | B50: 5150 | C50: 581 | D50: 33435 | E50: NOT PAID | F50: CARD PAYMENT | H50: =IF(D50>7000,"High",IF(D50>3000,"Medium","Low")) -> High | I50: =SUMIF(B:B,B50,D:D) -> 33435
A51: 3165b562-66f3-11ea-83de-7077813058ce | B51: 693 | C51: 336 | D51: 73589 | E51: NOT PAID | F51: CARD PAYMENT | H51: =IF(D51>7000,"High",IF(D51>3000,"Medium","Low")) -> High | I51: =SUMIF(B:B,B51,D:D) -> 73589
A52: 316678a4-66f3-11ea-b7d3-7077813058ce | B52: 9598 | C52: 504 | D52: 18598 | E52: PAID | F52: COD | G52: 30239 | H52: =IF(D52>7000,"High",IF(D52>3000,"Medium","Low")) -> High | I52: =SUMIF(B:B,B52,D:D) -> 18598
A53: 31673bc8-66f3-11ea-803a-7077813058ce | B53: 8103 | C53: 346 | D53: 23003 | E53: PAID | F53: CARD PAYMENT | G53: 39275 | H53: =IF(D53>7000,"High",IF(D53>3000,"Medium","Low")) -> High | I53: =SUMIF(B:B,B53,D:D) -> 23003
A54: 3167d7ee-66f3-11ea-a273-7077813058ce | B54: 8894 | C54: 135 | D54: 80901 | E54: NOT PAID | F54: CARD PAYMENT | H54: =IF(D54>7000,"High",IF(D54>3000,"Medium","Low")) -> High | I54: =SUMIF(B:B,B54,D:D) -> 80901
A55: 3168c236-66f3-11ea-ad73-7077813058ce | B55: 114 | C55: 822 | D55: 69113 | E55: PAID | F55: COD | G55: 33434 | H55: =IF(D55>7000,"High",IF(D55>3000,"Medium","Low")) -> High | I55: =SUMIF(B:B,B55,D:D) -> 69113
A56: 3169fa82-66f3-11ea-a4aa-7077813058ce | B56: 6546 | C56: 95 | D56: 26060 | E56: NOT PAID | F56: COD | H56: =IF(D56>7000,"High",IF(D56>3000,"Medium","Low")) -> High | I56: =SUMIF(B:B,B56,D:D) -> 26060
A57: 316abe90-66f3-11ea-b19a-7077813058ce | B57: 3571 | C57: 597 | D57: 25677 | E57: NOT PAID | F57: CARD PAYMENT | H57: =IF(D57>7000,"High",IF(D57>3000,"Medium","Low")) -> High | I57: =SUMIF(B:B,B57,D:D) -> 25677
A58: 316ba7f6-66f3-11ea-913f-7077813058ce | B58: 7316 | C58: 340 | D58: 62912 | E58: NOT PAID | F58: COD | H58: =IF(D58>7000,"High",IF(D58>3000,"Medium","Low")) -> High | I58: =SUMIF(B:B,B58,D:D) -> 62912
A59: 316c441e-66f3-11ea-89de-7077813058ce | B59: 2478 | C59: 905 | D59: 77649 | E59: PAID | F59: CARD PAYMENT | G59: 30589 | H59: =IF(D59>7000,"High",IF(D59>3000,"Medium","Low")) -> High | I59: =SUMIF(B:B,B59,D:D) -> 77649
A60: 316ce042-66f3-11ea-b223-7077813058ce | B60: 1215 | C60: 250 | D60: 73561 | E60: PAID | F60: COD | G60: 39012 | H60: =IF(D60>7000,"High",IF(D60>3000,"Medium","Low")) -> High | I60: =SUMIF(B:B,B60,D:D) -> 73561
A61: 316d7c6e-66f3-11ea-aad7-7077813058ce | B61: 5402 | C61: 400 | D61: 50357 | E61: NOT PAID | F61: COD | H61: =IF(D61>7000,"High",IF(D61>3000,"Medium","Low")) -> High | I61: =SUMIF(B:B,B61,D:D) -> 50357
A62: 316e8db8-66f3-11ea-88c1-7077813058ce | B62: 1647 | C62: 877 | D62: 61325 | E62: PAID | F62: CARD PAYMENT | G62: 36607 | H62: =IF(D62>7000,"High",IF(D62>3000,"Medium","Low")) -> High | I62: =SUMIF(B:B,B62,D:D) -> 61325
A63: 316f77f6-66f3-11ea-8aa2-7077813058ce | B63: 9423 | C63: 97 | D63: 76658 | E63: NOT PAID | F63: COD | H63: =IF(D63>7000,"High",IF(D63>3000,"Medium","Low")) -> High | I63: =SUMIF(B:B,B63,D:D) -> 76658
A64: 3170141c-66f3-11ea-97a3-7077813058ce | B64: 6404 | C64: 12 | D64: 35525 | E64: NOT PAID | F64: COD | H64: =IF(D64>7000,"High",IF(D64>3000,"Medium","Low")) -> High | I64: =SUMIF(B:B,B64,D:D) -> 35525
A65: 3170d834-66f3-11ea-b48e-7077813058ce | B65: 6767 | C65: 353 | D65: 12462 | E65: PAID | F65: COD | G65: 41186 | H65: =IF(D65>7000,"High",IF(D65>3000,"Medium","Low")) -> High | I65: =SUMIF(B:B,B65,D:D) -> 12462
A66: 31717452-66f3-11ea-9fcf-7077813058ce | B66: 1278 | C66: 856 | D66: 27105 | E66: PAID | F66: COD | G66: 28437 | H66: =IF(D66>7000,"High",IF(D66>3000,"Medium","Low")) -> High | I66: =SUMIF(B:B,B66,D:D) -> 27105
A67: 3172107a-66f3-11ea-ad07-7077813058ce | B67: 1334 | C67: 1 | D67: 99604 | E67: PAID | F67: COD | G67: 40512 | H67: =IF(D67>7000,"High",IF(D67>3000,"Medium","Low")) -> High | I67: =SUMIF(B:B,B67,D:D) -> 99604
A68: 3172d2fa-66f3-11ea-bad5-7077813058ce | B68: 8887 | C68: 390 | D68: 90449 | E68: PAID | F68: CARD PAYMENT | G68: 39881 | H68: =IF(D68>7000,"High",IF(D68>3000,"Medium","Low")) -> High | I68: =SUMIF(B:B,B68,D:D) -> 90449
A69: 3173e41e-66f3-11ea-b5f4-7077813058ce | B69: 9858 | C69: 446 | D69: 9520 | E69: NOT PAID | F69: COD | H69: =IF(D69>7000,"High",IF(D69>3000,"Medium","Low")) -> High | I69: =SUMIF(B:B,B69,D:D) -> 9520
A70: 3174f566-66f3-11ea-98c3-7077813058ce | B70: 9636 | C70: 32 | D70: 42210 | E70: NOT PAID | F70: CARD PAYMENT | H70: =IF(D70>7000,"High",IF(D70>3000,"Medium","Low")) -> High | I70: =SUMIF(B:B,B70,D:D) -> 42210
A71: 3175dfa2-66f3-11ea-b9d8-7077813058ce | B71: 9943 | C71: 420 | D71: 21639 | E71: NOT PAID | F71: COD | H71: =IF(D71>7000,"High",IF(D71>3000,"Medium","Low")) -> High | I71: =SUMIF(B:B,B71,D:D) -> 21639
A72: 31767bca-66f3-11ea-848b-7077813058ce | B72: 1246 | C72: 708 | D72: 58736 | E72: PAID | F72: COD | G72: 43677 | H72: =IF(D72>7000,"High",IF(D72>3000,"Medium","Low")) -> High | I72: =SUMIF(B:B,B72,D:D) -> 58736
A73: 317717f0-66f3-11ea-b57c-7077813058ce | B73: 4527 | C73: 227 | D73: 3951 | E73: PAID | F73: CARD PAYMENT | G73: 37261 | H73: =IF(D73>7000,"High",IF(D73>3000,"Medium","Low")) -> Medium | I73: =SUMIF(B:B,B73,D:D) -> 3951
A74: 3177db2e-66f3-11ea-99fe-7077813058ce | B74: 3782 | C74: 595 | D74: 69479 | E74: NOT PAID | F74: CARD PAYMENT | H74: =IF(D74>7000,"High",IF(D74>3000,"Medium","Low")) -> High | I74: =SUMIF(B:B,B74,D:D) -> 69479
A75: 3178c56c-66f3-11ea-9547-7077813058ce | B75: 6225 | C75: 211 | D75: 10366 | E75: PAID | F75: COD | G75: 39074 | H75: =IF(D75>7000,"High",IF(D75>3000,"Medium","Low")) -> High | I75: =SUMIF(B:B,B75,D:D) -> 10366
A76: 31796190-66f3-11ea-b0b6-7077813058ce | B76: 2257 | C76: 650 | D76: 10001 | E76: NOT PAID | F76: CARD PAYMENT | H76: =IF(D76>7000,"High",IF(D76>3000,"Medium","Low")) -> High | I76: =SUMIF(B:B,B76,D:D) -> 10001
A77: 3179fdb8-66f3-11ea-b117-7077813058ce | B77: 9177 | C77: 45 | D77: 15307 | E77: PAID | F77: CARD PAYMENT | G77: 35186 | H77: =IF(D77>7000,"High",IF(D77>3000,"Medium","Low")) -> High | I77: =SUMIF(B:B,B77,D:D) -> 15307
A78: 317ac112-66f3-11ea-96bf-7077813058ce | B78: 8703 | C78: 201 | D78: 68923 | E78: NOT PAID | F78: CARD PAYMENT | H78: =IF(D78>7000,"High",IF(D78>3000,"Medium","Low")) -> High | I78: =SUMIF(B:B,B78,D:D) -> 68923
A79: 317b8422-66f3-11ea-8b90-7077813058ce | B79: 3514 | C79: 564 | D79: 59651 | E79: PAID | F79: COD | G79: 38255 | H79: =IF(D79>7000,"High",IF(D79>3000,"Medium","Low")) -> High | I79: =SUMIF(B:B,B79,D:D) -> 59651
A80: 317c204a-66f3-11ea-b627-7077813058ce | B80: 3089 | C80: 138 | D80: 78953 | E80: NOT PAID | F80: CARD PAYMENT | H80: =IF(D80>7000,"High",IF(D80>3000,"Medium","Low")) -> High | I80: =SUMIF(B:B,B80,D:D) -> 78953
A81: 317ce378-66f3-11ea-b64a-7077813058ce | B81: 7253 | C81: 57 | D81: 89420 | E81: PAID | F81: COD | G81: 38048 | H81: =IF(D81>7000,"High",IF(D81>3000,"Medium","Low")) -> High | I81: =SUMIF(B:B,B81,D:D) -> 89420
A82: 317dcdc0-66f3-11ea-a3ce-7077813058ce | B82: 8786 | C82: 128 | D82: 50374 | E82: NOT PAID | F82: CARD PAYMENT | H82: =IF(D82>7000,"High",IF(D82>3000,"Medium","Low")) -> High | I82: =SUMIF(B:B,B82,D:D) -> 50374
A83: 317e69e2-66f3-11ea-8d1d-7077813058ce | B83: 1211 | C83: 33 | D83: 83102 | E83: NOT PAID | F83: COD | H83: =IF(D83>7000,"High",IF(D83>3000,"Medium","Low")) -> High | I83: =SUMIF(B:B,B83,D:D) -> 83102
A84: 317f5426-66f3-11ea-9e99-7077813058ce | B84: 359 | C84: 936 | D84: 62151 | E84: NOT PAID | F84: COD | H84: =IF(D84>7000,"High",IF(D84>3000,"Medium","Low")) -> High | I84: =SUMIF(B:B,B84,D:D) -> 62151
A85: 31803e5c-66f3-11ea-9cfa-7077813058ce | B85: 2066 | C85: 762 | D85: 84665 | E85: NOT PAID | F85: COD | H85: =IF(D85>7000,"High",IF(D85>3000,"Medium","Low")) -> High | I85: =SUMIF(B:B,B85,D:D) -> 84665
A86: 3180da86-66f3-11ea-a8db-7077813058ce | B86: 4322 | C86: 838 | D86: 1760 | E86: PAID | F86: COD | G86: 34934 | H86: =IF(D86>7000,"High",IF(D86>3000,"Medium","Low")) -> Low | I86: =SUMIF(B:B,B86,D:D) -> 1760
A87: 318176ac-66f3-11ea-8841-7077813058ce | B87: 7773 | C87: 215 | D87: 30239 | E87: PAID | F87: COD | G87: 31078 | H87: =IF(D87>7000,"High",IF(D87>3000,"Medium","Low")) -> High | I87: =SUMIF(B:B,B87,D:D) -> 30239
A88: 318260fe-66f3-11ea-a0f0-7077813058ce | B88: 6746 | C88: 818 | D88: 20194 | E88: PAID | F88: COD | G88: 39010 | H88: =IF(D88>7000,"High",IF(D88>3000,"Medium","Low")) -> High | I88: =SUMIF(B:B,B88,D:D) -> 20194
A89: 31832428-66f3-11ea-9902-7077813058ce | B89: 6732 | C89: 780 | D89: 58470 | E89: PAID | F89: COD | G89: 32798 | H89: =IF(D89>7000,"High",IF(D89>3000,"Medium","Low")) -> High | I89: =SUMIF(B:B,B89,D:D) -> 58470
A90: 31851fae-66f3-11ea-9f4d-7077813058ce | B90: 805 | C90: 40 | D90: 91926 | E90: NOT PAID | F90: COD | H90: =IF(D90>7000,"High",IF(D90>3000,"Medium","Low")) -> High | I90: =SUMIF(B:B,B90,D:D) -> 91926
A91: 31863106-66f3-11ea-8b2f-7077813058ce | B91: 7540 | C91: 366 | D91: 34797 | E91: PAID | F91: COD | G91: 29296 | H91: =IF(D91>7000,"High",IF(D91>3000,"Medium","Low")) -> High | I91: =SUMIF(B:B,B91,D:D) -> 34797
A92: 31876958-66f3-11ea-afcb-7077813058ce | B92: 5269 | C92: 678 | D92: 19346 | E92: NOT PAID | F92: COD | H92: =IF(D92>7000,"High",IF(D92>3000,"Medium","Low")) -> High | I92: =SUMIF(B:B,B92,D:D) -> 19346
A93: 31885382-66f3-11ea-b84f-7077813058ce | B93: 8404 | C93: 703 | D93: 35185 | E93: NOT PAID | F93: COD | H93: =IF(D93>7000,"High",IF(D93>3000,"Medium","Low")) -> High | I93: =SUMIF(B:B,B93,D:D) -> 35185
A94: 318916c0-66f3-11ea-8a7c-7077813058ce | B94: 519 | C94: 180 | D94: 7068 | E94: NOT PAID | F94: CARD PAYMENT | H94: =IF(D94>7000,"High",IF(D94>3000,"Medium","Low")) -> High | I94: =SUMIF(B:B,B94,D:D) -> 7068
A95: 318a2800-66f3-11ea-b639-7077813058ce | B95: 4060 | C95: 214 | D95: 96496 | E95: PAID | F95: CARD PAYMENT | G95: 31998 | H95: =IF(D95>7000,"High",IF(D95>3000,"Medium","Low")) -> High | I95: =SUMIF(B:B,B95,D:D) -> 96496
A96: 318b396c-66f3-11ea-9883-7077813058ce | B96: 8860 | C96: 408 | D96: 2988 | E96: PAID | F96: CARD PAYMENT | G96: 33127 | H96: =IF(D96>7000,"High",IF(D96>3000,"Medium","Low")) -> Low | I96: =SUMIF(B:B,B96,D:D) -> 2988
A97: 318cbfc6-66f3-11ea-b57f-7077813058ce | B97: 7164 | C97: 902 | D97: 83253 | E97: PAID | F97: COD | G97: 32768 | H97: =IF(D97>7000,"High",IF(D97>3000,"Medium","Low")) -> High | I97: =SUMIF(B:B,B97,D:D) -> 83253
A98: 318d82e8-66f3-11ea-9cca-7077813058ce | B98: 9792 | C98: 763 | D98: 87828 | E98: PAID | F98: COD | G98: 41891 | H98: =IF(D98>7000,"High",IF(D98>3000,"Medium","Low")) -> High | I98: =SUMIF(B:B,B98,D:D) -> 87828
A99: 318e4628-66f3-11ea-a70e-7077813058ce | B99: 9934 | C99: 168 | D99: 17035 | E99: PAID | F99: COD | G99: 35593 | H99: =IF(D99>7000,"High",IF(D99>3000,"Medium","Low")) -> High | I99: =SUMIF(B:B,B99,D:D) -> 17035
A100: 318f305e-66f3-11ea-b203-7077813058ce | B100: 1980 | C100: 723 | D100: 426 | E100: NOT PAID | F100: COD | H100: =IF(D100>7000,"High",IF(D100>3000,"Medium","Low")) -> Low | I100: =SUMIF(B:B,B100,D:D) -> 426
...

Sheet Membership
A1: M_ID | B1: Start_date | C1: End_date
A2: 31 | B2: 29164 | C2: 30452
A3: 495 | B3: 41908 | C3: 49045
A4: 795 | B4: 30612 | C4: 37450
A5: 33 | B5: 34491 | C5: 41061
A6: 882 | B6: 37044 | C6: 41846
A7: 657 | B7: 31583 | C7: 38920
A8: 761 | B8: 27099 | C8: 29521
A9: 20 | B9: 26261 | C9: 31010
A10: 356 | B10: 39964 | C10: 41914
A11: 301 | B11: 43183 | C11: 49672
A12: 450 | B12: 26914 | C12: 30324
A13: 782 | B13: 37161 | C13: 41937
... A201: 617 | B201: 33099 | C201: 34310

Sheet Top_5_Employees
A3: Row Labels | B3: Count of Shipment_Sh_ID
A4: 2 | B4: 1
A5: 7 | B5: 1
A6: 11 | B6: 1
A7: 18 | B7: 1
A8: 23 | B8: 1
A9: Grand Total | B9: 5

Sheet Employee_Shipment_Count
A3: Row Labels | B3: Count of Shipment_Sh_ID
A4: 2 | B4: 1
A5: 7 | B5: 1
A6: 11 | B6: 1
A7: 18 | B7: 1
A8: 23 | B8: 1
A9: 26 | B9: 1
A10: 31 | B10: 1
A11: 33 | B11: 1
A12: 47 | B12: 1
A13: 48 | B13: 1
A14: 49 | B14: 1
A15: 54 | B15: 1
... A203: 999 | B203: 1
A204: Grand Total | B204: 200

Sheet Designation_shipment_charge
A3: Row Labels | B3: Average of Shipment_charges
A4: In House logistics executive | B4: 717.5
A5: Grand Total | B5: 717.5

Sheet employee_manages_shipment
A1: Employee_E_ID | B1: Shipment_Sh_ID | C1: Status_Sh_ID | D1: Shipment_charges | E1: Designation
A2: 582 | B2: 690 | C2: 690 | D2: =VLOOKUP(B2,Shipment_Details!A:G,7,FALSE) -> 1210 | E2: =VLOOKUP(A2,Employee_Details!A:C,3,FALSE) -> Market analyst
A3: 396 | B3: 933 | C3: 933 | D3: =VLOOKUP(B3,Shipment_Details!A:G,7,FALSE) -> 1114 | E3: =VLOOKUP(A3,Employee_Details!A:C,3,FALSE) -> Chief finance officer
A4: 545 | B4: 261 | C4: 261 | D4: =VLOOKUP(B4,Shipment_Details!A:G,7,FALSE) -> 1020 | E4: =VLOOKUP(A4,Employee_Details!A:C,3,FALSE) -> Transport manager
A5: 770 | B5: 445 | C5: 445 | D5: =VLOOKUP(B5,Shipment_Details!A:G,7,FALSE) -> 1351 | E5: =VLOOKUP(A5,Employee_Details!A:C,3,FALSE) -> Warehouse manager
A6: 991 | B6: 722 | C6: 722 | D6: =VLOOKUP(B6,Shipment_Details!A:G,7,FALSE) -> 566 | E6: =VLOOKUP(A6,Employee_Details!A:C,3,FALSE) -> Branch manager
A7: 437 | B7: 129 | C7: 129 | D7: =VLOOKUP(B7,Shipment_Details!A:G,7,FALSE) -> 590 | E7: =VLOOKUP(A7,Employee_Details!A:C,3,FALSE) -> Project director
A8: 805 | B8: 489 | C8: 489 | D8: =VLOOKUP(B8,Shipment_Details!A:G,7,FALSE) -> 1407 | E8: =VLOOKUP(A8,Employee_Details!A:C,3,FALSE) -> HR manager
A9: 803 | B9: 165 | C9: 165 | D9: =VLOOKUP(B9,Shipment_Details!A:G,7,FALSE) -> 786 | E9: =VLOOKUP(A9,Employee_Details!A:C,3,FALSE) -> Material handling executive
A10: 295 | B10: 164 | C10: 164 | D10: =VLOOKUP(B10,Shipment_Details!A:G,7,FALSE) -> 855 | E10: =VLOOKUP(A10,Employee_Details!A:C,3,FALSE) -> Non-executive director
A11: 804 | B11: 364 | C11: 364 | D11: =VLOOKUP(B11,Shipment_Details!A:G,7,FALSE) -> 1182 | E11: =VLOOKUP(A11,Employee_Details!A:C,3,FALSE) -> Market analyst
A12: 54 | B12: 469 | C12: 469 | D12: =VLOOKUP(B12,Shipment_Details!A:G,7,FALSE) -> 25 | E12: =VLOOKUP(A12,Employee_Details!A:C,3,FALSE) -> In House logistics executive
A13: 853 | B13: 158 | C13: 158 | D13: =VLOOKUP(B13,Shipment_Details!A:G,7,FALSE) -> 861 | E13: =VLOOKUP(A13,Employee_Details!A:C,3,FALSE) -> Warehouse in charge
... A201: 957 | B201: 579 | C201: 579 | D201: =VLOOKUP(B201,Shipment_Details!A:G,7,FALSE) -> 1385 | E201: =VLOOKUP(A201,Employee_Details!A:C,3,FALSE) -> IT support executive

Sheet Employee_Details
A1: E_ID | B1: E_NAME | C1: E_DESIGNATION | D1: E_ADDR | E1: E_BRANCH | F1: E_CONT_NO | I1: Employee_ID | J1: Emploee Name | K1: Designation | L1: Branch
A2: 582 | B2: Harriette | C2: Market analyst | D2: 600 Block of PINE ST | E2: TX | F2: 2754220306 | I2: 295 | J2: =VLOOKUP(I2,$A$2:$F$201,2,FALSE) -> Kelli | K2: =VLOOKUP(I2,$A$2:$F$201,3,FALSE) -> Non-executive director | L2: =VLOOKUP(I2,$A$2:$F$201,5,FALSE) -> OH
A3: 396 | B3: Matthew | C3: Chief finance officer | D3: EDDY ST / MASON ST | E3: MA | F3: 4171197971
A4: 545 | B4: Geraldine | C4: Transport manager | D4: 800 Block of BRYANT ST | E4: CT | F4: 8354987185
A5: 770 | B5: Brenda | C5: Warehouse manager | D5: 3300 Block of JUDAH ST | E5: UT | F5: 6348759218
A6: 991 | B6: Malie | C6: Branch manager | D6: 3200 Block of GEARY BL | E6: OH | F6: 5096424869
A7: 437 | B7: Fred | C7: Project director | D7: VANNESS AV / MARKET ST | E7: MO | F7: 2378946703
A8: 805 | B8: Clay | C8: HR manager | D8: 1000 Block of BOSWORTH ST | E8: SD | F8: 8374022176
A9: 803 | B9: Alaysha | C9: Material handling executive | D9: 800 Block of GEARY ST | E9: UT | F9: 5698225463
A10: 295 | B10: Kelli | C10: Non-executive director | D10: BAY SHORE BL / JERROLD AV | E10: OH | F10: 1948808609
A11: 804 | B11: Ryker | C11: Market analyst | D11: 400 Block of LEAVENWORTH ST | E11: HI | F11: 5155277679
A12: 54 | B12: Johnnie | C12: In House logistics executive | D12: 100 Block of BRITTON ST | E12: RI | F12: 8682770474
A13: 853 | B13: Zykeria | C13: Warehouse in charge | D13: 2700 Block of PACIFIC AV | E13: VA | F13: 9334728554
A14: 902 | B14: Selma | C14: Head of marketing | D14: 900 Block of SANSOME ST | E14: KY | F14: 8568849220
... A201: 957 | B201: Valencia | C201: IT support executive | D201: 400 Block of EDDY ST | E201: CA | F201: 1160558300

Sheet Customer
A1: C_ID | B1: M_ID | C1: C_NAME | D1: C_EMAIL_ID | E1: C_TYPE | F1: C_ADDR | G1: C_CONT_NO | H1: Clean_Name | I1: Clean_Email | J1: Membership_start_date | K1: Membership_end_date | L1: Membership_Duration
A2: 230 | B2: 31 | C2: Mitchell | D2: Harriette42@ymail.com | E2: Internal Goods | F2: 2100 Block of 27TH AV | G2: 9961255787 | H2: =PROPER(Customer[[#This Row],[C_NAME]]) -> Mitchell | I2: =LOWER(Customer[[#This Row],[C_EMAIL_ID]]) -> harriette42@ymail.com | J2: =_xlfn.XLOOKUP(B2,Membership!A:A,Membership!B:B) -> 29164 | K2: =_xlfn.XLOOKUP(B2,Membership!A:A,Membership!C:C) -> 30452 | L2: =DATEDIF(J2,K2,"Y") -> 3
A3: 3189 | B3: 495 | C3: Reginald | D3: Matthew951@yahoo.co.in | E3: Wholesale | F3: 300 Block of ELLIS ST | G3: 3555176867 | H3: =PROPER(Customer[[#This Row],[C_NAME]]) -> Reginald | I3: =LOWER(Customer[[#This Row],[C_EMAIL_ID]]) -> matthew951@yahoo.co.in | J3: =_xlfn.XLOOKUP(B3,Membership!A:A,Membership!B:B) -> 41908 | K3: =_xlfn.XLOOKUP(B3,Membership!A:A,Membership!C:C) -> 49045 | L3: =DATEDIF(J3,K3,"Y") -> 19
A4: 2216 | B4: 795 | C4: Jaylene | D4: Geraldine867@ymail.co.in | E4: Retail | F4: 1000 Block of MISSION ST | G4: 9835395970 | H4: =PROPER(Customer[[#This Row],[C_NAME]]) -> Jaylene | I4: =LOWER(Customer[[#This Row],[C_EMAIL_ID]]) -> geraldine867@ymail.co.in | J4: =_xlfn.XLOOKUP(B4,Membership!A:A,Membership!B:B) -> 30612 | K4: =_xlfn.XLOOKUP(B4,Membership!A:A,Membership!C:C) -> 37450 | L4: =DATEDIF(J4,K4,"Y") -> 18
A5: 1904 | B5: 33 | C5: Stacie | D5: Brenda905@ymail.com | E5: Internal Goods | F5: 800 Block of BRYANT ST | G5: 3881250181 | H5: =PROPER(Customer[[#This Row],[C_NAME]]) -> Stacie | I5: =LOWER(Customer[[#This Row],[C_EMAIL_ID]]) -> brenda905@ymail.com | J5: =_xlfn.XLOOKUP(B5,Membership!A:A,Membership!B:B) -> 34491 | K5: =_xlfn.XLOOKUP(B5,Membership!A:A,Membership!C:C) -> 41061 | L5: =DATEDIF(J5,K5,"Y") -> 17
A6: 7342 | B6: 882 | C6: Jonathan | D6: Malie282@gmail.com | E6: Wholesale | F6: 0 Block of DRUMM ST | G6: 1507211823 | H6: =PROPER(Customer[[#This Row],[C_NAME]]) -> Jonathan | I6: =LOWER(Customer[[#This Row],[C_EMAIL_ID]]) -> malie282@gmail.com | J6: =_xlfn.XLOOKUP(B6,Membership!A:A,Membership!B:B) -> 37044 | K6: =_xlfn.XLOOKUP(B6,Membership!A:A,Membership!C:C) -> 41846 | L6: =DATEDIF(J6,K6,"Y") -> 13
A7: 7633 | B7: 657 | C7: Italia | D7: Fred847@google.co.in | E7: Internal Goods | F7: 3RD ST / FOLSOM ST | G7: 5612381477 | H7: =PROPER(Customer[[#This Row],[C_NAME]]) -> Italia | I7: =LOWER(Customer[[#This Row],[C_EMAIL_ID]]) -> fred847@google.co.in | J7: =_xlfn.XLOOKUP(B7,Membership!A:A,Membership!B:B) -> 31583 | K7: =_xlfn.XLOOKUP(B7,Membership!A:A,Membership!C:C) -> 38920 | L7: =DATEDIF(J7,K7,"Y") -> 20
A8: 2154 | B8: 761 | C8: Catherine | D8: Clay224@gmail.com | E8: Wholesale | F8: GOLDEN GATE AV / PARKER AV | G8: 8094222335 | H8: =PROPER(Customer[[#This Row],[C_NAME]]) -> Catherine | I8: =LOWER(Customer[[#This Row],[C_EMAIL_ID]]) -> clay224@gmail.com | J8: =_xlfn.XLOOKUP(B8,Membership!A:A,Membership!B:B) -> 27099 | K8: =_xlfn.XLOOKUP(B8,Membership!A:A,Membership!C:C) -> 29521 | L8: =DATEDIF(J8,K8,"Y") -> 6
A9: 5543 | B9: 20 | C9: Pierre | D9: Alaysha578@hotmail.com | E9: Wholesale | F9: 1400 Block of DEHARO ST | G9: 4133741447 | H9: =PROPER(Customer[[#This Row],[C_NAME]]) -> Pierre | I9: =LOWER(Customer[[#This Row],[C_EMAIL_ID]]) -> alaysha578@hotmail.com | J9: =_xlfn.XLOOKUP(B9,Membership!A:A,Membership!B:B) -> 26261 | K9: =_xlfn.XLOOKUP(B9,Membership!A:A,Membership!C:C) -> 31010 | L9: =DATEDIF(J9,K9,"Y") -> 13
A10: 2332 | B10: 356 | C10: Sheryl | D10: Kelli519@gmail.com | E10: Retail | F10: FOLSOM ST / 3RD ST | G10: 4399641006 | H10: =PROPER(Customer[[#This Row],[C_NAME]]) -> Sheryl | I10: =LOWER(Customer[[#This Row],[C_EMAIL_ID]]) -> kelli519@gmail.com | J10: =_xlfn.XLOOKUP(B10,Membership!A:A,Membership!B:B) -> 39964 | K10: =_xlfn.XLOOKUP(B10,Membership!A:A,Membership!C:C) -> 41914 | L10: =DATEDIF(J10,K10,"Y") -> 5
A11: 4094 | B11: 301 | C11: Rory | D11: Ryker154@hotmail.com | E11: Internal Goods | F11: 0 Block of THRIFT ST | G11: 7077259810 | H11: =PROPER(Customer[[#This Row],[C_NAME]]) -> Rory | I11: =LOWER(Customer[[#This Row],[C_EMAIL_ID]]) -> ryker154@hotmail.com | J11: =_xlfn.XLOOKUP(B11,Membership!A:A,Membership!B:B) -> 43183 | K11: =_xlfn.XLOOKUP(B11,Membership!A:A,Membership!C:C) -> 49672 | L11: =DATEDIF(J11,K11,"Y") -> 17
A12: 3042 | B12: 450 | C12: cecile | D12: Johnnie593@hotmail.com | E12: Wholesale | F12: 100 Block of GOLDEN GATE AV | G12: 1634188566 | H12: =PROPER(Customer[[#This Row],[C_NAME]]) -> Cecile | I12: =LOWER(Customer[[#This Row],[C_EMAIL_ID]]) -> johnnie593@hotmail.com | J12: =_xlfn.XLOOKUP(B12,Membership!A:A,Membership!B:B) -> 26914 | K12: =_xlfn.XLOOKUP(B12,Membership!A:A,Membership!C:C) -> 30324 | L12: =DATEDIF(J12,K12,"Y") -> 9
A13: 2220 | B13: 782 | C13: Monte | D13: Zykeria36@google.co.in | E13: Wholesale | F13: 2400 Block of DIAMOND ST | G13: 6963794710 | H13: =PROPER(Customer[[#This Row],[C_NAME]]) -> Monte | I13: =LOWER(Customer[[#This Row],[C_EMAIL_ID]]) -> zykeria36@google.co.in | J13: =_xlfn.XLOOKUP(B13,Membership!A:A,Membership!B:B) -> 37161 | K13: =_xlfn.XLOOKUP(B13,Membership!A:A,Membership!C:C) -> 41937 | L13: =DATEDIF(J13,K13,"Y") -> 13
... A201: 4892 | B201: 617 | C201: Jill | D201: Valencia714@yahoo.co.in | E201: Wholesale | F201: 14TH ST / VALENCIA ST | G201: 9062287896 | H201: =PROPER(Customer[[#This Row],[C_NAME]]) -> Jill | I201: =LOWER(Customer[[#This Row],[C_EMAIL_ID]]) -> valencia714@yahoo.co.in | J201: =_xlfn.XLOOKUP(B201,Membership!A:A,Membership!B:B) -> 33099 | K201: =_xlfn.XLOOKUP(B201,Membership!A:A,Membership!C:C) -> 34310 | L201: =DATEDIF(J201,K201,"Y") -> 3

Sheet Sheet1
